MANIFEST.in
bnc
bnf
bnf-cv
setup.py
BNfinder/BDE.py
BNfinder/BIC.py
BNfinder/CrossVal.py
BNfinder/MDL.py
BNfinder/MIT.py
BNfinder/Rocr.py
BNfinder/__init__.py
BNfinder/continuous.py
BNfinder/data.py
BNfinder/expression.py
BNfinder/graph.py
BNfinder/network.py
BNfinder/png.py
BNfinder/pstat.py
BNfinder/pyroc.py
BNfinder/score.py
BNfinder/stats.py
BNfinder/util.py
BNfinder.egg-info/PKG-INFO
BNfinder.egg-info/SOURCES.txt
BNfinder.egg-info/dependency_links.txt
BNfinder.egg-info/requires.txt
BNfinder.egg-info/top_level.txt
doc/Makefile
doc/distutils.sty
doc/doc_all.tex
doc/fancyhdr.sty
doc/fncychap.sty
doc/howto.cls
doc/ltxmarkup.sty
doc/man.bbl
doc/man.tex
doc/manual.cls
doc/manual.tex
doc/methods.tex
doc/pypaper.sty
doc/python.sty
doc/regul.bib
doc/regul_new.bib
doc/supp.tex
doc/tut.tex
doc/tut_art.tex
doc/tutor.tex
doc/underscore.sty
doc/data/.DS_Store
doc/data/input1.txt
doc/data/input1_p.txt
doc/data/input2.txt
doc/data/input3.txt
doc/data/input4.txt
doc/data/input5.txt
doc/data/input6a.txt
doc/data/input6b.txt
doc/data/input7.txt
doc/data/input8.txt
doc/data/output1.sif
doc/data/output1.txt
doc/data/output1w.sif
doc/data/output2.sif
doc/data/output3.sif
doc/data/output3.txt
doc/data/output4.sif
doc/data/output4.txt
doc/data/output5.sif
doc/data/output5.txt
doc/data/output6.sif
doc/data/output6.txt
doc/data/output7.sif
doc/data/output7mdl.sif
doc/data/sachs.inp
doc/data/sachs.sif
doc/data/sachs_w.sif
doc/data/test_set.txt
doc/data/training_set.txt
doc/img/ROC-K1.pdf
doc/img/ROC.png
doc/img/classificationresult.png
doc/img/dynamic.png
doc/img/dynamic2.png
doc/img/network1.png
doc/img/network2.png
doc/img/network3.png
doc/img/rock1.png
doc/img/static.png
doc/img/training.png