Metadata-Version: 1.1
Name: BNfinder
Version: 2.1.1
Summary: Bayes Net Finder: an efficient and exact method for learning bayesian networks
Home-page: http://bioputer.mimuw.edu.pl/software/bnf
Author: Bartek Wilczynski and Norbert Dojer
Author-email: bartek@mimuw.edu.pl
License: GNU GPL v.2
Download-URL: http://pypi.python.org/pypi/BNfinder/
Platform: UNKNOWN
